go3-0.2.3.dist-info/METADATA
go3-0.2.3.dist-info/WHEEL
go3-0.2.3.dist-info/licenses/LICENSE
go3/__init__.py
go3/go3.cpython-310-aarch64-linux-gnu.so
go3-0.2.3.dist-info/RECORD
