Metadata-Version: 2.4
Name: go3
Version: 0.2.3
Classifier: Programming Language :: Python
Classifier: Programming Language :: Rust
Classifier: Topic :: Scientific/Engineering :: Bio-Informatics
License-File: LICENSE
Summary: Semantic similarity computations using Gene Ontology with Rust performance
Author-email: Jose Luis Mellina Andreu <joseluis.mellinaa@um.es>
Requires-Python: >=3.7
Project-URL: Homepage, https://github.com/Mellandd/GO3
Project-URL: Repository, https://github.com/Mellandd/GO3
